setup.py
hexcrypt/__init__.py
hexcrypt/hexcrypt.py
hexcrypt.egg-info/PKG-INFO
hexcrypt.egg-info/SOURCES.txt
hexcrypt.egg-info/dependency_links.txt
hexcrypt.egg-info/not-zip-safe
hexcrypt.egg-info/top_level.txt